asapo_consumer.cpython-311-x86_64-linux-gnu.so
asapo_consumer.libs/libcom_err-2abe824b.so.2.1
asapo_consumer.libs/libcrypt-a115dc8d.so.1
asapo_consumer.libs/libcrypto-d3570994.so.1.0.2k
asapo_consumer.libs/libcurl-34c6b10f.so.4.3.0
asapo_consumer.libs/libgssapi_krb5-497db0c6.so.2.2
asapo_consumer.libs/libidn-97d26f25.so.11.6.11
asapo_consumer.libs/libk5crypto-b1f99d5c.so.3.1
asapo_consumer.libs/libkeyutils-dfe70bd6.so.1.5
asapo_consumer.libs/libkrb5-fcafa220.so.3.3
asapo_consumer.libs/libkrb5support-d0bcff84.so.0.1
asapo_consumer.libs/liblber-2-7eefa761.4.so.2.10.7
asapo_consumer.libs/libldap-2-b8523ca2.4.so.2.10.7
asapo_consumer.libs/libnspr4-4c890ba1.so
asapo_consumer.libs/libnss3-77677daf.so
asapo_consumer.libs/libnssutil3-3492aa84.so
asapo_consumer.libs/libpcre-9513aab5.so.1.2.0
asapo_consumer.libs/libplc4-690d9cce.so
asapo_consumer.libs/libplds4-c4b42550.so
asapo_consumer.libs/libsasl2-84219a89.so.3.0.0
asapo_consumer.libs/libselinux-0922c95c.so.1
asapo_consumer.libs/libsmime3-1ce58481.so
asapo_consumer.libs/libssh2-eaeb651a.so.1.0.1
asapo_consumer.libs/libssl-cd1d6220.so.1.0.2k
asapo_consumer.libs/libssl3-b5783e6f.so
asapo_consumer-25.3.0.dist-info/METADATA
asapo_consumer-25.3.0.dist-info/WHEEL
asapo_consumer-25.3.0.dist-info/top_level.txt
asapo_consumer-25.3.0.dist-info/RECORD
asapo_consumer-25.3.0.dist-info/licenses/CREDITS-3RD-PARTY-LICENSES.txt
asapo_consumer-25.3.0.dist-info/licenses/LICENSE.txt
